dtvr/__init__.py
dtvr/client.py
dtvr/timeutil.py
dtvr-0.0.3.dist-info/METADATA
dtvr-0.0.3.dist-info/WHEEL
dtvr-0.0.3.dist-info/RECORD
