Metadata-Version: 2.1
Name: dtvr
Version: 0.0.3
Summary: Python client for Dataverse
Author: Terraverse IT
Author-email: it@terraverse.info
Requires-Python: >=3.10,<4.0
Classifier: Programming Language :: Python :: 3
Classifier: Programming Language :: Python :: 3.10
Classifier: Programming Language :: Python :: 3.11
Classifier: Programming Language :: Python :: 3.12
Requires-Dist: pandas (>=2.2.2,<3.0.0)
Requires-Dist: requests (>=2.31.0,<3.0.0)
